{"stat.useItem.minecraft.bow":5451,"stat.useItem.chiselsandbits.chiseled_wood":2,"stat.pickup.extrautils2.redorchid":10,"stat.drop.minecraft.redstone":1,"stat.useItem.astralsorcery.itemchargedcrystalshovel":20,"stat.mineBlock.mowziesmobs.painted_acacia_slab":6,"stat.mineBlock.minecraft.stained_glass":3,"stat.drop.minecraft.enchanted_book":5,"stat.mineBlock.traverse.yellow_autumnal_sapling":1,"stat.mineBlock.minecraft.web":306,"stat.pickup.cfm.item_kebab_cooked":12,"stat.mineBlock.minecraftfuture.bee_nest":1,"stat.useItem.extrautils2.goldenlasso":70,"stat.craftItem.extrautils2.endershard":8,"stat.drop.minecraft.iron_sword":10,"stat.pickup.minecraft.rotten_flesh":2063,"stat.drop.animalium.wild_dog_pelt":1,"stat.craftItem.minecraftfuture.grindstone":3,"stat.useItem.chisel.marble":1189,"stat.drop.minecraft.leather_boots":1,"stat.useItem.minecraft.vine":36,"stat.pickup.minecraft.bucket":7,"stat.killEntity.Enderman":40,"stat.pickup.cfm.item_sausage_cooked":3,"stat.killEntity.wood_mimic":12,"stat.craftItem.minecraft.iron_shovel":36,"stat.mineBlock.extrautils2.redorchid":2,"stat.pickup.minecraft.brown_mushroom":14,"stat.craftItem.railcraft.nugget":24,"stat.drop.leatherworks.tannin_ball":1,"stat.killEntity.Villager":7,"stat.pickup.astralsorcery.blocklens":2,"stat.useItem.minecraft.spider_eye":1,"stat.pickup.betternether.cincinnasite_tile_large":6,"stat.useItem.minecraft.iron_pickaxe":13994,"stat.pickup.securitycraft.universal_block_remover":4,"stat.pickup.minecraftfuture.stripped_birch_log":1,"stat.pickup.minecraft.double_plant":87,"stat.pickup.treasure2.gold_key":3,"stat.craftItem.minecraft.glass_pane":32,"stat.mineBlock.chisel.marble2":5434,"stat.drop.chisel.stonebrick2":9,"stat.mineBlock.chisel.marble1":45,"stat.mineBlock.minecraft.sticky_piston":14,"stat.furnaceInteraction":886,"stat.entityKilledBy.bear":13,"stat.useItem.railcraft.tool_sword_steel":345,"stat.pickup.extrautils2.enderlilly":3,"stat.pickup.minecraft.nether_brick":76,"stat.pickup.securitycraft.cobblestone_mine":1,"stat.entityKilledBy.WitherSkeleton":2,"stat.pickup.minecraft.sponge":2,"stat.pickup.minecraft.hay_block":6,"stat.useItem.minecraft.fence":216,"stat.drop.cfm.stone_path":1,"stat.pickup.mca.rose_gold_ore":11,"stat.mineBlock.minecraft.fence":308,"stat.useItem.minecraft.wheat_seeds":552,"stat.mineBlock.minecraft.sea_lantern":61,"stat.mineBlock.astralsorcery.blockmarble":3480,"stat.drop.minecraft.cooked_fish":94,"stat.killEntity.Husk":11,"stat.mineBlock.roost.collector":1,"stat.mineBlock.zawa.sea_grass":8,"stat.pickup.minecraft.emerald":61,"stat.craftItem.securitycraft.laser_block":8,"stat.mineBlock.minecraftfuture.grindstone":14,"stat.pickup.minecraft.lever":6,"stat.deaths":888,"stat.pickup.minecraft.bowl":40,"stat.pickup.securitycraft.reinforced_dirt":13,"stat.pickup.mowziesmobs.barakoa_mask_fury":3,"stat.pickup.zawa.fur":8,"stat.pickup.minecraft.egg":1130,"stat.craftItem.minecraft.item_frame":10,"stat.craftItem.minecraft.iron_pickaxe":49,"stat.pickup.minecraft.glass_pane":53,"stat.useItem.chisel.planks-oak":210,"stat.pickup.minecraft.sea_lantern":39,"stat.pickup.minecraft.item_frame":14,"stat.pickup.zawa.cetacean_meat_raw":2,"stat.drop.minecraft.iron_ingot":5,"stat.craftItem.minecraft.repeater":27,"stat.fishCaught":1275,"stat.craftItem.minecraft.cooked_mutton":4,"stat.pickup.minecraft.cooked_mutton":665,"stat.chestOpened":3474,"stat.craftItem.leatherworks.leather_strip":16,"stat.craftItem.minecraft.sign":42,"stat.pickup.minecraft.iron_sword":45,"stat.pickup.treasure2.gold_coin":4,"stat.useItem.chisel.stonebrick":86,"stat.craftItem.minecraft.coal":2,"stat.pickup.minecraft.carrot":1291,"stat.useItem.securitycraft.reinforced_stairs_cobblestone":19,"stat.pickup.treasure2.silver_coin":21,"stat.crouchOneCm":81296,"stat.pickup.minecraft.rail":39,"stat.craftItem.minecraft.iron_ingot":1096,"stat.craftItem.malisisdoors.big_door_oak_3x3":1,"stat.craftingTableInteraction":1077,"stat.craftItem.extrautils2.decorativesolid":32,"stat.mineBlock.minecraft.wooden_pressure_plate":6,"stat.pickup.treasure2.crate_chest_moldy":1,"stat.pickup.minecraft.repeater":22,"stat.pickup.securitycraft.keypad_chest":27,"stat.pickup.treasure2.stone_key":2,"stat.mineBlock.minecraft.log2":32,"stat.pickup.zawa.lamp_top":3,"stat.pickup.minecraft.dye":2755,"stat.pickup.minecraft.planks":571,"stat.pickup.railcraft.track_kit":4,"stat.pickup.chisel.limestone2":1018,"stat.pickup.treasure2.ironbound_chest":2,"stat.craftItem.leatherworks.ender_pack":2,"stat.useItem.astralsorcery.itemchargedcrystalpickaxe":2,"stat.drop.minecraft.soul_sand":1,"stat.pickup.astralsorcery.itemchargedcrystalsword":1,"stat.pickup.leatherworks.ender_pack":1,"stat.craftItem.extrautils2.pipe":192,"stat.pickup.minecraftfuture.stripped_spruce_log":1,"stat.useItem.mowziesmobs.wrought_axe":399,"stat.pickup.minecraft.ice":85,"stat.useItem.animalium.rat_meat":1,"stat.pickup.securitycraft.reinforced_glass_block":2,"stat.drop.minecraft.rotten_flesh":83,"stat.pickup.minecraft.magma":315,"stat.mineBlock.zawa.bamboo":1,"stat.pickup.securitycraft.reinforced_stone":1418,"stat.pickup.astralsorcery.blockwell":1,"stat.drop.minecraft.glass_pane":3,"stat.drop.minecraft.sapling":2,"stat.pickup.minecraft.chicken":81,"stat.pickup.treasure2.gold_skull_chest":1,"stat.pickup.treasure2.painting_blocks_cobblestone":2,"stat.mineBlock.zawa.sea_urchin_tropical":2,"stat.useItem.minecraft.glass_pane":15,"stat.pickup.railcraft.equipment":1,"stat.drop.minecraft.fish":26,"stat.pickup.minecraft.coal_block":479,"stat.drop.minecraft.trapped_chest":1,"stat.craftItem.minecraft.bucket":16,"stat.useItem.minecraft.iron_sword":5891,"stat.craftItem.minecraft.planks":4472,"stat.mineBlock.minecraft.prismarine":105,"stat.useItem.securitycraft.universal_block_remover":414,"stat.craftItem.minecraft.fishing_rod":2,"stat.pickup.minecraft.stone_sword":4,"stat.useItem.minecraft.stonebrick":258,"stat.pickup.minecraft.book":114,"stat.craftItem.minecraft.wooden_door":18,"stat.mineBlock.minecraft.waterlily":25,"stat.mineBlock.securitycraft.cobblestone_mine":1,"stat.pickup.railcraft.nugget":15,"stat.pickup.minecraft.iron_door":15,"stat.mineBlock.betternether.cincinnasite_bricks":48,"stat.pickup.betternether.stalagnate_seed":2,"stat.pickup.minecraft.cooked_fish":248,"stat.pickup.extrautils2.pipe":8,"stat.craftItem.minecraft.cobblestone":9,"stat.mineBlock.astralsorcery.blockworldilluminator":7,"stat.craftItem.minecraft.spruce_door":69,"stat.drop.chisel.chisel_diamond":3,"stat.pickup.minecraft.tripwire_hook":367,"stat.drop.astralsorcery.blockmarble":18,"stat.pickup.treasure2.white_pearl":2,"stat.pickup.zawa.fire_coral":1,"stat.mineBlock.minecraft.cobblestone":1930,"stat.killEntity.bee":1,"stat.mineBlock.minecraft.pumpkin":1,"stat.pickup.minecraft.stone_pickaxe":6,"stat.pickup.minecraft.flint":501,"stat.useItem.chiselsandbits.block_bit":368,"stat.pickup.traverse.yellow_autumnal_sapling":1,"stat.killEntity.firefly":4,"stat.pickup.minecraft.leather_chestplate":14,"stat.pickup.extrautils2.compoundbow":1,"stat.mineBlock.railcraft.track_flex_strap_iron":2,"stat.mineBlock.treasure2.ironbound_chest":2,"stat.mineBlock.chisel.cobblestone2":493,"stat.drop.minecraft.cobblestone":227,"stat.pickup.minecraft.cooked_porkchop":74,"stat.mineBlock.chisel.marble":236,"stat.useItem.tombstone.tablet_of_recall":14,"stat.useItem.minecraft.stone_slab2":2668,"stat.useItem.astralsorcery.blockworldilluminator":1,"stat.pickup.astralsorcery.blockattunementrelay":9,"stat.pickup.forge.bucketfilled":1,"stat.drop.securitycraft.reinforced_stone":2,"stat.pickup.minecraft.iron_boots":15,"stat.pickup.animalium.rat_meat_cooked":71,"stat.pickup.minecraft.diamond_horse_armor":1,"stat.pickup.minecraft.stone_hoe":2,"stat.craftItem.minecraft.furnace":192,"stat.pickup.minecraft.golden_axe":1,"stat.drop.cgm.assault_rifle":2,"stat.mineBlock.minecraft.clay":570,"stat.mineBlock.astralsorcery.blockritualpedestal":2,"stat.useItem.minecraft.brick_block":10,"stat.mineBlock.cfm.castle_netting":1,"stat.useItem.minecraft.wooden_slab":282,"stat.drop.minecraft.spider_eye":9,"stat.useItem.minecraft.iron_door":9,"stat.craftItem.minecraft.iron_block":36,"stat.useItem.chesttransporter.chesttransporter_iron":8,"stat.craftItem.railcraft.tool_sword_steel":1,"stat.craftItem.minecraft.stonebrick":32,"stat.pickup.astralsorcery.itemskyresonator":3,"stat.drop.chiselsandbits.chiseled_rock":1,"stat.killEntity.Creeper":234,"stat.mineBlock.leatherworks.drying_rack_spruce":37,"stat.mineBlock.betternether.smoker":1,"stat.pickup.comforts.sleeping_bag":110,"stat.mineBlock.zawa.kelp":5,"stat.pickup.tombstone.crafting_ingredient":392,"stat.entityKilledBy.Skeleton":126,"stat.useItem.minecraftfuture.trident":18,"stat.killEntity.Squid":19,"stat.sprintOneCm":25832679,"stat.mineBlock.minecraft.stone_slab":57,"stat.useItem.minecraft.hay_block":9,"stat.drop.minecraft.leather":1,"stat.mineBlock.railcraft.equipment":1,"stat.pickup.betternether.lucis_spore":3,"stat.pickup.extrautils2.passivegenerator":84,"stat.craftItem.extrautils2.indexer":2,"stat.mineBlock.betternether.pig_statue_01":1,"stat.pickup.mowziesmobs.barakoa_mask_fear":3,"stat.useItem.securitycraft.keypad_item":9,"stat.pickup.minecraft.leather_leggings":12,"stat.pickup.treasure2.ruby_lock":4,"stat.mineBlock.zawa.gracilaria":1,"stat.entityKilledBy.wood_mimic":1,"stat.pickup.minecraft.sugar":8,"stat.drop.tombstone.grave_key":7,"stat.pickup.tombstone.grave_key":6,"stat.craftItem.minecraft.emerald":7,"stat.killEntity.Zombie":1255,"stat.craftItem.minecraft.dye":863,"stat.craftItem.minecraft.diamond_axe":1,"stat.mineBlock.minecraft.gold_ore":210,"stat.craftItem.leatherworks.tannin_ball":14,"stat.drop.minecraft.diamond_pickaxe":24,"stat.pickup.minecraft.wheat":1032,"stat.mineBlock.minecraft.mossy_cobblestone":2,"stat.mineBlock.astralsorcery.blockmarblestairs":75,"stat.drop.astralsorcery.itemcraftingcomponent":1,"stat.pickup.minecraft.sign":41,"stat.pickup.chisel.planks-acacia":3,"stat.drop.zawa.beeplant":20,"stat.pickup.minecraft.obsidian":22,"stat.mineBlock.betternether.cincinnasite_bricks_pillar":87,"stat.useItem.minecraft.heavy_weighted_pressure_plate":6,"stat.useItem.astralsorcery.itemchargedcrystalsword":4,"stat.pickup.betternether.black_bush":1,"stat.pickup.minecraft.coal":6855,"stat.pickup.minecraft.iron_ingot":1260,"stat.craftItem.minecraft.lever":1,"stat.drop.minecraft.diamond_sword":10,"stat.pickup.minecraft.gunpowder":888,"stat.mineBlock.treasure2.gold_strongbox":8,"stat.useItem.astralsorcery.blockritualpedestal":2,"stat.pickup.minecraft.dirt":12273,"stat.drop.minecraft.iron_shovel":7,"stat.craftItem.malisisdoors.big_door_rusty_3x3":1,"stat.pickup.leatherworks.debarked_log_spruce":2,"stat.useItem.astralsorcery.blockblackmarble":30,"stat.pickup.leatherworks.rawhide_pig":19,"stat.pickup.leatherworks.rawhide_cow":113,"stat.mineBlock.minecraft.lapis_ore":167,"stat.pickup.minecraft.red_sandstone":13,"stat.pickup.minecraft.iron_axe":28,"stat.pickup.minecraft.cookie":59,"stat.drop.animalium.rat_meat_cooked":7,"stat.brewingstandInteraction":28,"stat.useItem.minecraft.stone_brick_stairs":5,"stat.craftItem.extrautils2.goldenlasso":4,"stat.mineBlock.minecraft.torch":1118,"stat.mineBlock.minecraft.red_flower":238,"stat.craftItem.malisisdoors.verticalhatch":1,"stat.tradedWithVillager":8,"stat.pickup.minecraft.magma_cream":17,"stat.craftItem.astralsorcery.itemcraftingcomponent":4,"stat.useItem.securitycraft.reinforced_stone":1815,"stat.craftItem.minecraft.comparator":15,"stat.pickup.betternether.cincinnasite_bricks":48,"stat.entityKilledBy.piranha":40,"stat.craftItem.minecraft.glowstone":64,"stat.mineBlock.minecraftfuture.flowerblue":8,"stat.pickup.astralsorcery.blockcustomore":22,"stat.craftItem.malisisdoors.big_door_acacia_3x3":1,"stat.pickup.minecraft.rabbit_hide":1,"stat.pickup.treasure2.gold_strongbox":8,"stat.pickup.minecraft.shulker_shell":1,"stat.mineBlock.betternether.nether_brick_tile_stairs":47,"stat.pickup.zawa.bladderwrack":4,"stat.mineBlock.securitycraft.dirt_mine":1,"stat.drop.minecraft.wheat":260,"stat.pickup.minecraft.diamond_pickaxe":26,"stat.pickup.treasure2.metallurgists_key":1,"stat.useItem.minecraft.pumpkin":6,"stat.craftItem.chiselsandbits.chisel_iron":2,"stat.useItem.minecraft.tnt":13,"stat.useItem.minecraft.lava_bucket":19,"stat.mineBlock.minecraftfuture.bamboo":4,"stat.pickup.minecraft.rabbit_foot":1,"stat.useItem.minecraft.item_frame":9,"stat.pickup.mowziesmobs.barako_mask":4,"stat.pickup.chiselsandbits.chiseled_ground":2,"stat.useItem.zawa.large_meat_cooked":1,"stat.drop.minecraft.egg":3,"stat.useItem.minecraft.redstone_ore":31,"stat.pickup.minecraft.cooked_beef":330,"stat.mineBlock.opframe.opframe":5,"stat.killEntity.Stray":4,"stat.pickup.cfm.door_mat":2,"stat.pickup.treasure2.thiefs_lock_pick":1,"stat.mineBlock.betternether.bone_mushroom":4,"stat.mineBlock.extrautils2.minichest":1,"stat.pickup.minecraft.dark_oak_stairs":4,"stat.mobKills":5383,"stat.pickup.minecraft.diamond_boots":2,"stat.mineBlock.minecraft.bookshelf":17,"stat.pickup.securitycraft.diamond_mine":1,"stat.mineBlock.treasure2.skull_chest":11,"stat.useItem.minecraft.boat":3,"stat.craftItem.minecraft.lead":2,"stat.pickup.minecraft.diamond":1002,"stat.pickup.minecraft.beetroot_seeds":65,"stat.craftItem.mca.whistle":1,"stat.mineBlock.zawa.lamp_base":1,"stat.pickup.minecraft.brown_mushroom_block":2,"stat.pickup.roost.roost":1,"stat.pickup.astralsorcery.blockmarble":3191,"stat.craftItem.tombstone.book_of_disenchantment":1,"stat.pickup.mowziesmobs.naga_fang":2,"stat.pickup.zawa.small_sea_urchin":1,"stat.useItem.minecraft.bookshelf":33,"stat.useItem.cfm.stone_path":21,"stat.killEntity.Blaze":67,"stat.drop.chisel.marble":3,"stat.pickup.minecraft.golden_boots":13,"stat.pickup.minecraft.glowstone_dust":1136,"stat.drop.minecraft.wooden_door":2,"stat.drop.treasure2.thiefs_lock_pick":2,"stat.drop.astralsorcery.itemskyresonator":1,"stat.mineBlock.minecraft.stone_brick_stairs":9,"stat.mineBlock.minecraft.nether_brick_fence":7,"stat.useItem.minecraft.golden_sword":16,"stat.drop.mowziesmobs.wrought_axe":11,"stat.mineBlock.treasure2.crate_chest_moldy":1,"stat.pickup.astralsorcery.itemchargedcrystalpickaxe":1,"stat.pickup.betternether.nether_brick_wall":17,"stat.pickup.betternether.smoker":2,"stat.pickup.minecraft.chainmail_chestplate":25,"stat.pickup.mowziesmobs.barakoa_mask_misery":2,"stat.useItem.chisel.basalt":8,"stat.mineBlock.minecraft.sand":5000,"stat.pickup.securitycraft.reinforced_cobblestone":18,"stat.mineBlock.betternether.nether_brick_tile_large":16,"stat.pickup.chiselsandbits.chiseled_wood":9,"stat.pickup.treasure2.iron_lock":13,"stat.useItem.securitycraft.keypad_chest":5,"stat.pickup.treasure2.skull_and_crossbones":2,"stat.craftItem.spartanshields.shield_basic_wood":1,"stat.hopperInspected":1173,"stat.drop.minecraft.diamond":46,"stat.pickup.astralsorcery.itemjournal":16,"stat.mineBlock.betternether.bone_wall":3,"stat.pickup.minecraft.ghast_tear":2,"stat.pickup.minecraft.armor_stand":1,"stat.trappedChestTriggered":1145,"stat.drop.animalium.rat_meat":15,"stat.pickup.zawa.cetacean_meat_cooked":1,"stat.mineBlock.zawa.bladderwrack":2,"stat.drop.leatherworks.drying_rack_oak":1,"stat.craftItem.minecraft.acacia_stairs":8,"stat.drop.astralsorcery.blockmarblestairs":1,"stat.pickup.minecraft.wooden_button":1,"stat.mineBlock.minecraft.lapis_block":6,"stat.pickup.cfm.item_ink_cartridge":189,"stat.drop.astralsorcery.itemarchitectwand":3,"stat.useItem.extrautils2.pipe":79,"stat.useItem.minecraft.cooked_mutton":154,"stat.pickup.minecraft.totem_of_undying":1,"stat.pickup.betternether.black_apple":1,"stat.mineBlock.malisisdoors.big_door_acacia_3x3":5,"stat.drop.minecraft.fishing_rod":18,"stat.mineBlock.railcraft.track_outfitted":4,"stat.useItem.comforts.sleeping_bag":65,"stat.pickup.minecraft.stone_stairs":143,"stat.pickup.variedcommodities.emerald_sword":1,"stat.mineBlock.cfm.printer":2,"stat.pickup.minecraft.acacia_stairs":7,"stat.pickup.minecraft.pumpkin_seeds":3,"stat.pickup.minecraft.golden_carrot":4,"stat.drop.minecraft.fireworks":3,"stat.craftItem.chisel.chisel_diamond":5,"stat.pickup.minecraft.saddle":106,"stat.mineBlock.minecraft.soul_sand":385,"stat.drop.chiselsandbits.block_bit":17,"stat.pickup.minecraft.blaze_rod":57,"stat.useItem.railcraft.generic":48,"stat.craftItem.securitycraft.keypad_item":23,"stat.drop.minecraft.chest":1,"stat.pickup.minecraft.netherrack":936,"stat.pickup.treasure2.treasure_tool":10,"stat.mineBlock.betternether.cincinnasite_pot":1,"stat.pickup.zawa.kibble":1,"stat.useItem.minecraft.fish":21,"stat.drop.minecraft.hopper":8,"stat.pickup.minecraft.waterlily":133,"stat.mineBlock.minecraft.ice":92,"stat.useItem.chisel.stonebrick1":5,"stat.useItem.chisel.stonebrick2":3297,"stat.pickup.chisel.marblepillar":2,"stat.pickup.zawa.gorilla_hide":11,"stat.pickup.minecraft.brick_stairs":2,"stat.pickup.leatherworks.leather_sheet":2,"stat.mineBlock.zawa.lettuce_coral":2,"stat.drop.minecraft.stone":25,"stat.useItem.minecraft.trapped_chest":34,"stat.pickup.leatherworks.rawhide_wolf":4,"stat.pickup.minecraft.golden_leggings":18,"stat.pickup.zawa.large_sea_urchin":1,"stat.pickup.minecraft.heavy_weighted_pressure_plate":6,"stat.mineBlock.treasure2.safe":7,"stat.pickup.chisel.futura":93,"stat.pickup.betternether.barrel_cactus":2,"stat.pickup.securitycraft.universal_block_modifier":3,"stat.craftItem.treasure2.treasure_tool":1,"stat.craftItem.securitycraft.remote_access_sentry":1,"stat.drop.minecraft.bone":2,"stat.pickup.zawa.reptile_meat_cooked":2,"stat.useItem.minecraft.furnace":9,"stat.craftItem.extrautils2.indexerremote":1,"stat.craftItem.extrautils2.ingredients":8,"stat.pickup.treasure2.emerald_key":1,"stat.pickup.minecraft.iron_leggings":12,"stat.killEntity.Llama":2,"stat.pickup.tombstone.tablet_of_recall":13,"stat.mineBlock.minecraft.gravel":1219,"stat.useItem.chisel.planks-spruce":796,"stat.craftItem.cfm.stone_path":8,"stat.pickup.zawa.dried_bamboo":6,"stat.drop.minecraft.reeds":7,"stat.pickup.betternether.pig_statue_01":1,"stat.mineBlock.malisisdoors.big_door_iron_3x3":4,"stat.craftItem.minecraft.leather":5,"stat.drop.minecraft.iron_axe":7,"stat.useItem.minecraft.torch":2173,"stat.pickup.minecraft.golden_apple":357,"stat.craftItem.minecraft.redstone_block":15,"stat.craftItem.minecraft.stone_stairs":100,"stat.pickup.minecraft.crafting_table":48,"stat.useItem.minecraft.log":154,"stat.useItem.minecraft.comparator":33,"stat.craftItem.minecraft.crafting_table":54,"stat.mineBlock.treasure2.wood_chest":4,"stat.useItem.betternether.cincinnasite_axe_diamond":1,"stat.craftItem.minecraft.boat":2,"stat.pickup.minecraft.iron_hoe":26,"stat.mineBlock.minecraft.emerald_ore":8,"stat.pickup.extrautils2.grocket":4,"stat.pickup.chisel.basalt":4,"stat.mineBlock.chisel.stonebrick":12,"stat.pickup.treasure2.skeleton_key":1,"stat.useItem.minecraft.cooked_fish":1832,"stat.drop.minecraft.sign":1,"stat.drop.minecraft.stonebrick":3,"stat.pickup.astralsorcery.blockaltar":6,"stat.pickup.zawa.large_sea_anemone":2,"stat.craftItem.minecraft.stone_button":204,"stat.useItem.treasure2.thiefs_lock_pick":1,"stat.pickup.chisel.planks-spruce":115,"stat.pickup.minecraft.sapling":394,"stat.pickup.roost.chicken":16,"stat.craftItem.astralsorcery.blockaltar":1,"stat.drop.minecraft.bow":24,"stat.pickup.minecraft.beetroot":23,"stat.pickup.leatherworks.pack_brown":5,"stat.pickup.malisisdoors.big_door_acacia_3x3":6,"stat.killEntity.WitherSkeleton":10,"stat.drop.comforts.sleeping_bag":8,"stat.pickup.extrautils2.trashcan":5,"stat.useItem.minecraft.wooden_pressure_plate":6,"stat.pickup.spartanshields.shield_tower_diamond":2,"stat.pickup.treasure2.wood_key":3,"stat.useItem.securitycraft.remote_access_sentry":32,"stat.craftItem.minecraft.sugar":3,"stat.pickup.betternether.nether_mycelium":4,"stat.useItem.chesttransporter.chesttransporter":78,"stat.drop.minecraft.bucket":1,"stat.drop.mowziesmobs.wrought_helmet":3,"stat.useItem.minecraft.baked_potato":27,"stat.pickup.minecraft.stone_slab":45,"stat.pickup.minecraft.yellow_flower":165,"stat.useItem.minecraft.fishing_rod":1785,"stat.drop.minecraft.stone_pickaxe":2,"stat.craftItem.minecraft.diamond_chestplate":2,"stat.pickup.zawa.bird_meat_cooked":8,"stat.pickup.minecraft.bone":747,"stat.craftItem.minecraft.sticky_piston":4,"stat.pickup.minecraft.redstone_torch":6,"stat.horseOneCm":4538911,"stat.useItem.astralsorcery.blockmarblestairs":131,"stat.useItem.minecraft.log2":4,"stat.pickup.chisel.planks-oak":64,"stat.drop.minecraft.prismarine_crystals":8,"stat.mineBlock.minecraft.black_shulker_box":1,"stat.mineBlock.traverse.yellow_autumnal_leaves":2,"stat.mineBlock.minecraft.brown_mushroom":4,"stat.useItem.minecraft.diamond_sword":4039,"stat.pickup.treasure2.sapphire_key":2,"stat.craftItem.securitycraft.sentry":6,"stat.craftItem.extrautils2.glasscutter":1,"stat.climbOneCm":78719,"stat.drop.chisel.limestone2":34,"stat.pickup.chisel.marble":304,"stat.pickup.treasure2.sapphire":49,"stat.enderchestOpened":136,"stat.pickup.minecraft.golden_helmet":14,"stat.drop.minecraft.quartz":23,"stat.pickup.zawa.bird_meat":1,"stat.useItem.minecraft.red_flower":3,"stat.pickup.minecraft.cooked_rabbit":2,"stat.drop.leatherworks.debarked_log_spruce":1,"stat.drop.chisel.planks-birch":4,"stat.pickup.minecraft.anvil":2,"stat.useItem.minecraft.iron_ore":24,"stat.craftItem.minecraft.stone_pickaxe":40,"stat.pickup.minecraft.cobblestone":20724,"stat.pickup.minecraft.soul_sand":308,"stat.useItem.astralsorcery.blockmarbleslab":5,"stat.useItem.minecraft.cooked_beef":204,"stat.pickup.minecraft.cactus":206,"stat.mineBlock.treasure2.iron_strongbox":6,"stat.pickup.minecraft.redstone":3395,"stat.craftItem.minecraft.dispenser":6,"stat.mineBlock.minecraft.iron_ore":2008,"stat.craftItem.minecraft.book":85,"stat.pickup.securitycraft.keypad_item":3,"stat.craftItem.minecraft.acacia_door":6,"stat.drop.minecraft.coal":6,"stat.craftItem.extrautils2.screen":3,"stat.pickup.minecraft.cake":1,"stat.craftItem.astralsorcery.blockmarbleslab":6,"stat.drop.extrautils2.ingredients":13,"stat.drop.minecraft.dirt":124,"stat.pickup.minecraft.iron_shovel":33,"stat.useItem.minecraft.cooked_porkchop":129,"stat.pickup.minecraft.carpet":3,"stat.pickup.minecraft.trapdoor":2,"stat.pickup.minecraft.diamond_shovel":2,"stat.pickup.chesttransporter.chesttransporter_iron":1,"stat.craftItem.treasure2.ruby_key":1,"stat.useItem.minecraft.sea_lantern":9,"stat.pickup.chisel.glass":208,"stat.pickup.minecraft.nether_star":64,"stat.useItem.minecraft.spruce_fence":194,"stat.pickup.zawa.blubber":18,"stat.mineBlock.zawa.mixed_coral_plates":1,"stat.pickup.minecraft.paper":86,"stat.craftItem.malisisdoors.big_door_iron_3x3":1,"stat.craftItem.minecraft.stick":2198,"stat.useItem.extrautils2.passivegenerator":322,"stat.drop.minecraftfuture.trident":4,"stat.craftItem.minecraft.gold_nugget":54,"stat.mineBlock.malisisdoors.big_door_spruce_3x3":1,"stat.pickup.minecraft.grass":75,"stat.useItem.minecraft.stone_pressure_plate":3,"stat.mineBlock.betternether.reeds_block":1,"stat.pickup.treasure2.crate_chest":1,"stat.pickup.minecraft.diamond_chestplate":1,"stat.mineBlock.chisel.planks-acacia":2,"stat.entityKilledBy.Creeper":55,"stat.useItem.chiselsandbits.chisel_stone":2,"stat.mineBlock.minecraft.planks":387,"stat.drop":1891,"stat.drop.astralsorcery.itemtunedrockcrystal":4,"stat.killEntity.Sheep":11,"stat.pickup.leatherworks.tannin_ball":14,"stat.pickup.minecraft.golden_chestplate":13,"stat.mineBlock.astralsorcery.blockmachine":1,"stat.craftItem.securitycraft.universal_block_remover":1,"stat.drop.minecraft.bread":30,"stat.craftItem.chesttransporter.chesttransporter":81,"stat.craftItem.minecraft.piston":4,"stat.pickup.securitycraft.remote_access_sentry":4,"stat.mineBlock.traverse.red_autumnal_leaves":1,"stat.useItem.extrautils2.machine":1,"stat.mineBlock.betternether.cincinnasite_brick_plate":18,"stat.useItem.chisel.marblepillar":2,"stat.drop.minecraft.cooked_beef":2,"stat.killEntity.Slime":36,"stat.mineBlock.minecraft.anvil":3,"stat.mineBlock.cfm.door_bell":1,"stat.useItem.minecraft.waterlily":38,"stat.useItem.minecraft.apple":4,"stat.mineBlock.minecraft.deadbush":1,"stat.useItem.minecraft.black_glazed_terracotta":90,"stat.useItem.minecraft.carpet":1,"stat.useItem.minecraft.potion":3,"stat.pickup.extrautils2.ironwood_sapling":1,"stat.pickup.minecraft.fence":353,"stat.craftItem.minecraft.iron_helmet":1,"stat.drop.minecraft.glass":2,"stat.boatOneCm":573475,"stat.pickup.astralsorcery.itemusabledust":58,"stat.craftItem.minecraft.flint_and_steel":2,"stat.mineBlock.minecraft.leaves2":87,"stat.mineBlock.minecraft.stone_stairs":135,"stat.mineBlock.minecraft.furnace":17,"stat.pickup.treasure2.ruby_key":3,"stat.pickup.zawa.lamp_middle":1,"stat.pickup.minecraft.prismarine_shard":25,"stat.pickup.minecraft.end_crystal":5,"stat.pickup.leatherworks.broken_leather_chestplate":1,"stat.killEntity.CaveSpider":56,"stat.pickup.astralsorcery.itemlinkingtool":2,"stat.useItem.tombstone.grave_key":1217,"stat.pickup.minecraft.stained_glass":3,"stat.damageDealt":338862,"stat.pickup.cfm.printer":2,"stat.craftItem.minecraft.anvil":4,"stat.mineBlock.minecraft.nether_brick_stairs":33,"stat.pickup.securitycraft.alarm":3,"stat.useItem.minecraft.crafting_table":3,"stat.useItem.minecraft.cyan_glazed_terracotta":52,"stat.craftItem.minecraft.stone_shovel":1,"stat.pickup.minecraft.boat":1,"stat.craftItem.railcraft.ingot":7,"stat.pickup.minecraft.stick":444,"stat.pickup.minecraft.spectral_arrow":2,"stat.craftItem.minecraftfuture.dye":16,"stat.pickup.zawa.elephant_leather":16,"stat.pickup.cgm.handgun":3,"stat.drop.treasure2.silver_coin":1,"stat.pickup.railcraft.ingot":118,"stat.craftItem.minecraft.diamond_boots":2,"stat.useItem.cfm.item_sausage_cooked":2,"stat.pickup.betternether.bone_mushroom":17,"stat.mineBlock.leatherworks.debarked_log_oak":1,"stat.drop.chisel.glass":5,"stat.mineBlock.zawa.large_sea_anemone":2,"stat.useItem.minecraft.cactus":63,"stat.pickup.betternether.netherrack_moss":4,"stat.useItem.betternether.cincinnasite_stairs":17,"stat.pickup.zawa.atv":9,"stat.killEntity.Chicken":106,"stat.drop.minecraft.crafting_table":1,"stat.mineBlock.minecraft.quartz_ore":61,"stat.craftItem.minecraft.tnt":13,"stat.entityKilledBy.ElderGuardian":2,"stat.pickup.minecraft.dragon_breath":1,"stat.craftItem.minecraft.fence":9,"stat.entityKilledBy.Husk":2,"stat.pickup.mowziesmobs.barakoa_mask_bliss":3,"stat.useItem.minecraft.golden_apple":109,"stat.pickup.treasure2.skull_chest":11,"stat.mineBlock.minecraft.leaves":734,"stat.pickup.cfm.stone_path":16,"stat.mineBlock.railcraft.generic":162,"stat.mineBlock.minecraft.bone_block":12,"stat.mineBlock.minecraft.hay_block":6,"stat.pickup.betternether.nether_brick_tile_large":14,"stat.pickup.treasure2.skull_sword":1,"stat.pickup.astralsorcery.itemwand":6,"stat.mineBlock.treasure2.pirate_chest":9,"stat.pickup.minecraft.wooden_slab":360,"stat.leaveGame":622,"stat.killEntity.Parrot":2,"stat.pickup.astralsorcery.itemarchitectwand":6,"stat.pickup.extrautils2.indexerremote":8,"stat.useItem.minecraft.glowstone":63,"stat.mineBlock.minecraft.sandstone":52,"stat.craftItem.minecraft.ender_eye":7,"stat.killEntity.PigZombie":5,"stat.craftItem.minecraft.shield":1,"stat.craftItem.minecraft.stone_pressure_plate":7,"stat.entityKilledBy.PigZombie":4,"stat.pickup.betternether.bone_stairs":15,"stat.mineBlock.astralsorcery.blockcustomflower":2,"stat.pickup.treasure2.iron_strongbox":6,"stat.mineBlock.minecraft.red_sandstone":6,"stat.pickup.zawa.pangolin_scale":4,"stat.pickup.minecraft.brick_block":125,"stat.pickup.animalium.wild_dog_pelt":49,"stat.craftItem.spartanshields.shield_basic_diamond":1,"stat.mineBlock.minecraft.wooden_slab":194,"stat.pickup.minecraft.leather_boots":55,"stat.killEntity.Witch":28,"stat.drop.chesttransporter.chesttransporter":3,"stat.pickup.chisel.chisel_iron":19,"stat.drop.minecraft.tnt":2,"stat.craftItem.minecraft.wooden_pickaxe":2,"stat.craftItem.astralsorcery.itemjournal":1,"stat.craftItem.minecraft.iron_door":18,"stat.useItem.minecraft.iron_shovel":11042,"stat.mineBlock.minecraft.brick_block":124,"stat.pickup.railcraft.track_flex_abandoned":3,"stat.pickup.leatherworks.rawhide_horse":2,"stat.craftItem.minecraft.bed":5,"stat.pickup.treasure2.gold_lock":12,"stat.pickup.extrautils2.chickenring":2,"stat.mineBlock.minecraft.vine":4,"stat.mineBlock.minecraft.hopper":103,"stat.mineBlock.treasure2.ruby_ore":2,"stat.mineBlock.minecraft.rail":4,"stat.killEntity.ZombieVillager":57,"stat.pickup.mowziesmobs.painted_acacia_slab":5,"stat.mineBlock.traverse.fir_log":10,"stat.mineBlock.betternether.cincinnasite_stairs":20,"stat.drop.minecraft.red_flower":6,"stat.mineBlock.treasure2.sapphire_ore":8,"stat.useItem.minecraft.double_plant":47,"stat.pickup.minecraft.prismarine":127,"stat.pickup.minecraft.beef":122,"stat.pickup.chisel.stonebrick":11,"stat.pickup.minecraft.leather_helmet":3,"stat.pickup.minecraft.cauldron":2,"stat.pickup.mowziesmobs.wrought_helmet":9,"stat.useItem.minecraft.ice":4,"stat.pickup.minecraft.potion":98,"stat.drop.railcraft.tool_shovel_steel":1,"stat.pickup.securitycraft.reinforced_planks":139,"stat.pickup.treasure2.dread_pirate_chest":7,"stat.pickup.mowziesmobs.barakoa_mask_rage":3,"stat.useItem.animalium.bear_meat":1,"stat.pickup.betternether.cincinnasite_pillar":36,"stat.pickup.securitycraft.universal_block_reinforcer_lvl1":1,"stat.useItem.chiselsandbits.chiseled_rock":2,"stat.useItem.minecraft.dye":325,"stat.pickup.securitycraft.universal_block_reinforcer_lvl3":1,"stat.useItem.minecraft.beef":6,"stat.pickup.elevatorid.elevator_black":2,"stat.mineBlock.minecraft.stone_pressure_plate":4,"stat.pickup.minecraftfuture.sweetberry":1,"stat.craftItem.zawa.tire":2,"stat.pickup.astralsorcery.blockmarblestairs":106,"stat.drop.minecraft.glass_bottle":1,"stat.drop.minecraft.torch":2,"stat.pickup.chisel.marble1":170,"stat.pickup.chisel.marble2":6055,"stat.mineBlock.minecraft.tallgrass":1005,"stat.useItem.minecraft.splash_potion":9,"stat.mineBlock.chisel.planks-birch":260,"stat.useItem.props.props":391,"stat.craftItem.minecraft.light_weighted_pressure_plate":6,"stat.useItem.minecraft.stone":2077,"stat.drop.extrautils2.indexerremote":8,"stat.pickup.minecraft.arrow":963,"stat.pickup.minecraft.wooden_pressure_plate":6,"stat.mineBlock.chisel.dirt":2,"stat.killEntity.Ghast":12,"stat.pickup.extrautils2.compressedcobblestone":1,"stat.useItem.minecraft.clay":1,"stat.drop.minecraft.iron_pickaxe":11,"stat.pickup.astralsorcery.itemgrapplewand":17,"stat.mineBlock.elevatorid.elevator_white":1,"stat.useItem.cfm.printer":13,"stat.pickup.chisel.basalt2":256,"stat.pickup.treasure2.sapphire_lock":3,"stat.mineBlock.minecraft.chest":107,"stat.useItem.zawa.cetacean_meat_cooked":2,"stat.pickup.cgm.assault_rifle":4,"stat.craftItem.minecraft.hopper":55,"stat.pickup.minecraft.nether_brick_fence":5,"stat.useItem.chisel.marble1":240,"stat.useItem.chisel.marble2":771,"stat.useItem.minecraft.reeds":80,"stat.pickup.betternether.stalagnate_stem":5,"stat.drop.astralsorcery.blockattunementrelay":2,"stat.mineBlock.railcraft.track_flex_abandoned":3,"stat.craftItem.minecraft.diamond_shovel":3,"stat.pickup.minecraft.wheat_seeds":1832,"stat.pickup.chisel.cobblestone":47,"stat.mineBlock.minecraft.glass":242,"stat.pickup.malisisdoors.big_door_spruce_3x3":1,"stat.mineBlock.betternether.nether_mycelium":2,"stat.mineBlock.minecraft.dirt":13038,"stat.pickup.minecraft.poisonous_potato":12,"stat.useItem.minecraft.bread":71,"stat.craftItem.securitycraft.portable_radar":8,"stat.useItem.minecraft.cobblestone":5454,"stat.useItem.minecraft.gravel":100,"stat.mineBlock.minecraft.double_plant":64,"stat.mineBlock.chisel.futura":93,"stat.mineBlock.betternether.cincinnasite_ore":6,"stat.pickup.treasure2.wood_lock":5,"stat.pickup.minecraft.iron_pickaxe":38,"stat.drop.minecraft.carrot":361,"stat.mineBlock.astralsorcery.blockattunementrelay":2,"stat.pickup.treasure2.diamond_key":1,"stat.craftItem.minecraft.gold_ingot":80,"stat.mineBlock.cfm.door_bell_birch":9,"stat.mineBlock.chisel.basalt":4,"stat.pickup.minecraft.hopper":101,"stat.mineBlock.chisel.stonebrick1":4,"stat.craftItem.chisel.chisel_iron":21,"stat.mineBlock.chisel.stonebrick2":1462,"stat.pickup.treasure2.ruby":9,"stat.craftItem.minecraft.brewing_stand":1,"stat.pickup.minecraft.apple":50,"stat.useItem.minecraft.fireworks":25,"stat.craftItem.securitycraft.door_indestructible_iron_item":5,"stat.useItem.astralsorcery.itemarchitectwand":294,"stat.killEntity.ElderGuardian":2,"stat.itemEnchanted":5,"stat.useItem.betternether.cincinnasite_fire_bowl":6,"stat.pickup.railcraft.track_flex_strap_iron":2,"stat.mineBlock.minecraft.log":241,"stat.mineBlock.minecraft.heavy_weighted_pressure_plate":6,"stat.pickup.treasure2.emerald_lock":4,"stat.useItem.chisel.basalt2":21,"stat.useItem.minecraft.wooden_door":12,"stat.useItem.minecraft.spruce_door":29,"stat.mineBlock.extrautils2.enderlilly":1,"stat.craftItem.minecraft.paper":561,"stat.pickup.railcraft.tool_crowbar_iron":4,"stat.pickup.minecraft.red_flower":265,"stat.mineBlock.zawa.fire_coral":1,"stat.pickup.minecraft.wool":29,"stat.mineBlock.chisel.marblepillar":2,"stat.craftItem.minecraft.trapped_chest":40,"stat.drop.minecraft.grass":1,"stat.pickup.astralsorcery.blockblackmarble":3,"stat.pickup.minecraft.trapped_chest":18,"stat.pickup.railcraft.ore":25,"stat.cakeSlicesEaten":51,"stat.craftItem.astralsorcery.blockmarblestairs":84,"stat.craftItem.leatherworks.barrel_oak":2,"stat.craftItem.minecraft.diamond_leggings":2,"stat.craftItem.leatherworks.drying_rack_oak":13,"stat.mineBlock.minecraft.acacia_stairs":5,"stat.useItem.minecraft.iron_axe":2533,"stat.mineBlock.minecraft.yellow_flower":169,"stat.entityKilledBy.Witch":2,"stat.mineBlock.betternether.barrel_cactus":1,"stat.craftItem.minecraft.wool":36,"stat.pickup.chesttransporter.chesttransporter":1,"stat.mineBlock.astralsorcery.blockcustomore":40,"stat.mineBlock.betternether.cincinnasite_pillar":40,"stat.pickup.zawa.animal_net":14,"stat.mineBlock.betternether.nether_cactus":2,"stat.pickup.minecraft.enchanted_book":128,"stat.pickup.minecraft.glowstone":35,"stat.useItem.securitycraft.dirt_mine":27,"stat.craftItem.minecraft.arrow":376,"stat.pickup.minecraft.sticky_piston":18,"stat.useItem.minecraft.cookie":38,"stat.pickup.minecraft.bow":231,"stat.mineBlock.chisel.cobblestone":29,"stat.useItem.minecraft.egg":1259,"stat.pickup.treasure2.eye_patch":1,"stat.craftItem.minecraft.spruce_boat":7,"stat.pickup.minecraft.pumpkin_pie":3,"stat.pickup.animalium.rat_meat":95,"stat.pickup.minecraft.coal_ore":29,"stat.craftItem.minecraft.cooked_beef":60,"stat.craftItem.treasure2.sapphire_key":1,"stat.mineBlock.minecraft.obsidian":14,"stat.drop.chiselsandbits.chiseled_wood":1,"stat.pickup.minecraft.shears":1,"stat.craftItem.minecraft.bow":12,"stat.pickup.animalium.bear_meat":6,"stat.flyOneCm":18021289,"stat.pickup.zawa.zebra_leather":10,"stat.pickup.minecraft.sandstone":34,"stat.pickup.zawa.rhino_hide":4,"stat.pickup.minecraft.nether_brick_stairs":32,"stat.pickup.minecraft.fish":6547,"stat.pickup.betternether.cincinnasite_ore":1,"stat.timeSinceDeath":88180,"stat.mineBlock.betternether.bone_stairs":16,"stat.craftItem.tombstone.scroll_buff":1,"stat.craftItem.leatherworks.crafting_leather_scraped":128,"stat.pickup.chiselsandbits.block_bit":175,"stat.killEntity.Bat":7,"stat.useItem.minecraft.potato":30,"stat.pickup.betternether.red_mold":4,"stat.pickup.minecraft.chainmail_helmet":18,"stat.pickup.minecraft.nether_wart":10,"stat.pickup.betternether.bone_wall":2,"stat.mineBlock.astralsorcery.blockblackmarble":2,"stat.pickup.minecraft.spruce_fence":41,"stat.mineBlock.minecraft.enchanting_table":1,"stat.killEntity.Wolf":2,"stat.craftItem.leatherworks.drying_rack_spruce":16,"stat.drop.astralsorcery.itemrockcrystalsimple":14,"stat.mineBlock.minecraft.coal_ore":3145,"stat.pickup.zawa.bush_meat_cooked":10,"stat.pickup.minecraft.shield":2,"stat.craftItem.minecraft.stone_hoe":2,"stat.pickup.extrautils2.ingredients":179,"stat.talkedToVillager":208,"stat.drop.minecraft.baked_potato":16,"stat.mineBlock.minecraft.red_mushroom_block":14,"stat.pickup.minecraft.string":986,"stat.pickup.leatherworks.bark_oak":4,"stat.pickup.securitycraft.codebreaker":1,"stat.useItem.betternether.cincinnasite_bricks":12,"stat.pickup.railcraft.tool_sword_steel":2,"stat.pickup.leatherworks.debarked_log_oak":1,"stat.pickup.astralsorcery.blockmachine":1,"stat.pickup.betternether.bone_block":16,"stat.useItem.minecraft.diamond_shovel":1126,"stat.pickup.minecraft.chest_minecart":2,"stat.pickup.securitycraft.portable_radar":8,"stat.pickup.minecraft.bone_block":11,"stat.mineBlock.extrautils2.machine":1,"stat.craftItem.zawa.atv":1,"stat.mineBlock.treasure2.dread_pirate_chest":6,"stat.mineBlock.minecraft.diamond_ore":219,"stat.pickup.minecraft.fireworks":58,"stat.pickup.cfm.door_bell":1,"stat.pickup.railcraft.ore_metal_poor":47,"stat.pickup.minecraftfuture.trident":16,"stat.pickup.zawa.sea_grass":2,"stat.craftItem.minecraft.wooden_pressure_plate":9,"stat.pickup.zawa.gracilaria":3,"stat.pickup.leatherworks.drying_rack_oak":17,"stat.craftItem.minecraft.golden_sword":1,"stat.useItem.chiselsandbits.chiseled_ground":2,"stat.useItem.minecraft.ladder":5,"stat.pickup.minecraft.snowball":7,"stat.killEntity.Guardian":6,"stat.craftItem.securitycraft.scanner_door_item":5,"stat.entityKilledBy.rat":17,"stat.pickup.chisel.stonebrick2":1558,"stat.diveOneCm":7082253,"stat.pickup.chisel.stonebrick1":4,"stat.useItem.leatherworks.sealed_barrel_acacia":140,"stat.drop.securitycraft.sentry":7,"stat.useItem.minecraft.sticky_piston":11,"stat.pickup.extrautils2.machine":1,"stat.mineBlock.minecraft.stone_button":7,"stat.pickup.railcraft.armor_overalls":1,"stat.useItem.minecraft.chicken":1,"stat.useItem.securitycraft.sentry":24,"stat.drop.extrautils2.goldenlasso":1,"stat.pickup.astralsorcery.blockritualpedestal":5,"stat.useItem.minecraft.rotten_flesh":2,"stat.craftItem.zawa.animal_net":44,"stat.craftItem.minecraft.diamond_sword":4,"stat.jump":92732,"stat.useItem.minecraft.sand":53,"stat.drop.animalium.bear_claw_paxel":1,"stat.useItem.astralsorcery.itemcrystalshovel":3,"stat.pickup.animalium.bear_claw":36,"stat.pickup.minecraft.hopper_minecart":1,"stat.pickup.extrautils2.indexer":2,"stat.pickup.malisisdoors.big_door_oak_3x3":6,"stat.craftItem.minecraft.torch":1316,"stat.mineBlock.roost.roost":1,"stat.craftItem.minecraft.fermented_spider_eye":2,"stat.drop.zawa.animal_net":6,"stat.useItem.minecraft.glass":312,"stat.pickup.minecraft.gold_ore":238,"stat.useItem.minecraft.sapling":252,"stat.craftItem.leatherworks.leather_sheet":11,"stat.mineBlock.betternether.bone_block":16,"stat.pickup.mowziesmobs.painted_acacia":15,"stat.mineBlock.minecraft.glass_pane":35,"stat.damageTaken":380567,"stat.useItem.extrautils2.ironwood_sapling":2,"stat.mineBlock.minecraft.sapling":33,"stat.mineBlock.astralsorcery.blocklens":2,"stat.pickup.minecraft.log2":559,"stat.mineBlock.minecraft.sandstone_stairs":2,"stat.entityKilledBy.ZombieVillager":6,"stat.pickup.minecraft.bed":8,"stat.pickup.opframe.opframe":5,"stat.pickup.minecraft.concrete":7,"stat.useItem.chisel.glass":3019,"stat.pickup.minecraft.quartz_block":22,"stat.pickup.minecraft.potato":1285,"stat.entityKilledBy.Zombie":161,"stat.mineBlock.minecraftfuture.stripped_birch_log":1,"stat.killEntity.Silverfish":50,"stat.drop.chiselsandbits.chisel_stone":1,"stat.entityKilledBy.LavaSlime":3,"stat.craftItem.minecraft.stone_slab":42,"stat.craftItem.securitycraft.universal_block_reinforcer_lvl1":5,"stat.animalsBred":83,"stat.useItem.minecraft.chest":193,"stat.pickup.railcraft.tool_axe_steel":2,"stat.mineBlock.betternether.cincinnasite_fire_bowl":11,"stat.pickup.traverse.fir_log":10,"stat.shulkerBoxOpened":2,"stat.craftItem.minecraft.iron_chestplate":1,"stat.pickup.minecraft.baked_potato":21,"stat.useItem.extrautils2.compoundbow":19,"stat.pickup.minecraft.ender_pearl":92,"stat.drop.securitycraft.codebreaker":1,"stat.pickup.minecraft.ladder":7,"stat.useItem.minecraft.netherrack":36,"stat.mineBlock.minecraft.tnt":5,"stat.craftItem.minecraft.bookshelf":47,"stat.useItem.chisel.planks-birch":310,"stat.mineBlock.minecraft.stonebrick":14,"stat.pickup.leatherworks.broken_leather_helmet":1,"stat.craftItem.securitycraft.universal_key_changer":1,"stat.mineBlock.minecraft.glowstone":214,"stat.craftItem.railcraft.tool_shovel_steel":1,"stat.craftItem.minecraft.shears":3,"stat.drop.props.props":5,"stat.pickup.betternether.cincinnasite_pedestal":1,"stat.mineBlock.elevatorid.elevator_black":2,"stat.pickup.props.props":345,"stat.pickup.minecraft.iron_horse_armor":1,"stat.pickup.minecraft.torch":3993,"stat.mineBlock.betternether.cincinnasite_tile_large":6,"stat.mineBlock.astralsorcery.blockcustomsandore":16,"stat.pickup.minecraft.spruce_boat":3,"stat.drop.minecraft.shears":1,"stat.craftItem.securitycraft.remote_access_mine":1,"stat.pickup.railcraft.tool_spike_maul_iron":1,"stat.drop.minecraft.waterlily":1,"stat.craftItem.minecraft.iron_axe":4,"stat.useItem.minecraft.lead":1,"stat.craftItem.leatherworks.pack_brown":2,"stat.pickup.astralsorcery.itemconstellationpaper":12,"stat.pickup.minecraft.lapis_block":6,"stat.useItem.railcraft.anvil":2,"stat.pickup.minecraftfuture.flowerblue":6,"stat.useItem.minecraft.mutton":2,"stat.pickup.minecraft.fishing_rod":125,"stat.mineBlock.extrautils2.compressedcobblestone":1,"stat.useItem.minecraft.planks":278,"stat.useItem.minecraft.nether_brick_stairs":30,"stat.pickup.minecraft.porkchop":16,"stat.pickup.minecraft.glass":1244,"stat.pickup.minecraft.blaze_powder":18,"stat.craftItem.astralsorcery.itemwand":1,"stat.useItem.minecraft.water_bucket":273,"stat.pickup.minecraft.sand":3263,"stat.entityKilledBy.Spider":32,"stat.pickup.betternether.egg_plant":2,"stat.killEntity.bear":28,"stat.pickup.minecraft.name_tag":295,"stat.mineBlock.malisisdoors.big_door_oak_3x3":6,"stat.pickup.minecraft.activator_rail":2,"stat.mineBlock.treasure2.compressor_chest":2,"stat.aviateOneCm":26921851,"stat.mineBlock.leatherworks.drying_rack_oak":6,"stat.pickup.chisel.cobblestone2":499,"stat.useItem.minecraft.ender_pearl":1,"stat.craftItem.extrautils2.resonator":1,"stat.pickup.elevatorid.elevator_white":1,"stat.craftItem.minecraft.cooked_fish":479,"stat.drop.astralsorcery.itemjournal":12,"stat.useItem.securitycraft.reinforced_cobblestone":2,"stat.mineBlock.chisel.planks-spruce":57,"stat.pickup.securitycraft.laser_block":10,"stat.pickup.astralsorcery.itemcape":1,"stat.pickup.traverse.orange_autumnal_sapling":4,"stat.pickup.betternether.orange_mushroom":1,"stat.craftItem.minecraft.golden_carrot":1,"stat.mineBlock.minecraft.dark_oak_stairs":8,"stat.useItem.astralsorcery.blockattunementrelay":11,"stat.pickup.astralsorcery.blockworldilluminator":8,"stat.pickup.malisisdoors.big_door_iron_3x3":22,"stat.pickup.railcraft.generic":172,"stat.pickup.betternether.cincinnasite_bricks_pillar":85,"stat.mineBlock.minecraftfuture.stripped_spruce_log":1,"stat.pickup.treasure2.diamond_lock":3,"stat.pickup.minecraftfuture.grindstone":14,"stat.pickup.minecraft.furnace":29,"stat.useItem.minecraft.redstone":71,"stat.useItem.railcraft.tool_shovel_steel":74,"stat.useItem.treasure2.dread_pirate_chest":4,"stat.pickup.mowziesmobs.wrought_axe":16,"stat.pickup.minecraft.iron_chestplate":21,"stat.useItem.minecraft.stone_stairs":154,"stat.pickup.minecraft.skull":10,"stat.mineBlock.extrautils2.passivegenerator":80,"stat.pickup.minecraft.acacia_door":3,"stat.pickup.treasure2.wood_chest":4,"stat.mineBlock.betternether.cincinnasite_pedestal":1,"stat.useItem.extrautils2.indexerremote":8,"stat.mineBlock.minecraft.brick_stairs":2,"stat.pickup.chiselsandbits.chiseled_rock":10,"stat.useItem.minecraft.hopper":273,"stat.craftItem.minecraft.heavy_weighted_pressure_plate":40,"stat.mineBlock.minecraft.oak_stairs":5,"stat.drop.securitycraft.universal_block_reinforcer_lvl3":1,"stat.entityKilledBy.wild_dog":134,"stat.drop.minecraft.golden_carrot":4,"stat.pickup.betternether.cincinnasite_fire_bowl":13,"stat.playOneMinute":18997273,"stat.drop.securitycraft.universal_block_reinforcer_lvl1":1,"stat.pickup.betternether.cincinnasite_brick_plate":18,"stat.mineBlock.minecraft.brown_mushroom_block":2,"stat.pickup.minecraft.iron_bars":6,"stat.pickup.chisel.dirt":2,"stat.pickup.zawa.ivory_tusk":9,"stat.mineBlock.minecraft.netherrack":1572,"stat.craftItem.mca.engagement_ring":1,"stat.pickup.zawa.toxin_sac":1,"stat.mineBlock.treasure2.gold_skull_chest":1,"stat.drop.minecraft.flint":1,"stat.mineBlock.treasure2.crate_chest":2,"stat.pickup.minecraft.cooked_chicken":5,"stat.drop.animalium.bear_meat_cooked":1,"stat.pickup.railcraft.plate":8,"stat.fallOneCm":1519626,"stat.drop.minecraft.dye":3,"stat.pickup.cgm.ammo":1089,"stat.craftItem.minecraft.chest":274,"stat.useItem.minecraft.nether_brick_fence":4,"stat.mineBlock.minecraft.lever":4,"stat.pickup.minecraft.red_mushroom":3,"stat.useItem.minecraft.iron_hoe":342,"stat.craftItem.astralsorcery.blockblackmarble":32,"stat.pickup.chiselsandbits.chisel_stone":2,"stat.pickup.minecraft.comparator":20,"stat.pickup.minecraft.feather":173,"stat.mineBlock.zawa.small_sea_anemone":1,"stat.mineBlock.extrautils2.indexer":2,"stat.pickup.cfm.door_bell_birch":14,"stat.pickup.betternether.reeds_block":1,"stat.pickup.zawa.kelp":8,"stat.mineBlock.minecraft.spruce_fence":29,"stat.pickup.minecraft.lead":28,"stat.useItem.minecraft.stone_pickaxe":4538,"stat.craftItem.minecraft.iron_leggings":1,"stat.pickup.betternether.cincinnasite":12,"stat.killEntity.Rabbit":1,"stat.useItem.securitycraft.remote_access_mine":14,"stat.pickup.minecraft.redstone_ore":1,"stat.entityKilledBy.Ghast":2,"stat.pickup.zawa.large_meat_cooked":6,"stat.pickup.minecraft.chainmail_boots":15,"stat.pickup.securitycraft.scanner_door_item":9,"stat.mineBlock.betternether.nether_brick_wall":17,"stat.drop.minecraft.stick":4,"stat.craftItem.securitycraft.dirt_mine":30,"stat.useItem.minecraft.iron_bars":2,"stat.pickup.minecraft.record_13":2,"stat.mineBlock.minecraft.monster_egg":3,"stat.useItem.animalium.bear_meat_cooked":5,"stat.drop.tombstone.crafting_ingredient":6,"stat.drop.minecraft.stone_brick_stairs":1,"stat.pickup.mowziesmobs.ice_crystal":4,"stat.mineBlock.railcraft.ore":148,"stat.killEntity.LavaSlime":53,"stat.pickup.minecraft.log":2959,"stat.mineBlock.railcraft.ore_metal_poor":56,"stat.useItem.astralsorcery.blocklens":1,"stat.drop.tombstone.tablet_of_recall":1,"stat.pickup.zawa.bamboo":1,"stat.pickup.minecraft.chainmail_leggings":11,"stat.mineBlock.chisel.glass":408,"stat.drop.mowziesmobs.ice_crystal":3,"stat.pickup.minecraft.wooden_door":19,"stat.entityKilledBy.Enderman":21,"stat.craftItem.treasure2.thiefs_lock_pick":238,"stat.useItem.zawa.beeplant":8,"stat.pickup.railcraft.fluid_bottle_creosote":36,"stat.mineBlock.leatherworks.debarked_log_spruce":2,"stat.craftItem.props.props":1,"stat.drop.leatherworks.pack_brown":4,"stat.pickup.leatherworks.crafting_leather_soaked":15,"stat.drop.securitycraft.universal_block_remover":2,"stat.mineBlock.cfm.stone_path":15,"stat.useItem.securitycraft.cobblestone_mine":5,"stat.pickup.leatherworks.broken_leather_boots":4,"stat.craftItem.minecraft.cooked_chicken":58,"stat.useItem.minecraft.stone_hoe":150,"stat.drop.treasure2.sapphire_key":1,"stat.useItem.minecraft.beetroot_seeds":2,"stat.sneakTime":135200,"stat.entityKilledBy.Blaze":10,"stat.mineBlock.railcraft.ore_metal":278,"stat.useItem.minecraft.beetroot":2,"stat.pickup.minecraft.chest":99,"stat.craftItem.minecraft.enchanting_table":1,"stat.drop.minecraft.sugar":1,"stat.pickup.treasure2.painting_blocks_water":1,"stat.pickup.minecraft.stone_pressure_plate":7,"stat.pickup.extrautils2.book":1,"stat.drop.minecraft.beetroot":1,"stat.useItem.minecraft.repeater":34,"stat.pickup.leatherworks.bark_spruce":14,"stat.pickup.securitycraft.sentry":13,"stat.craftItem.minecraft.stone_brick_stairs":4,"stat.drop.securitycraft.remote_access_sentry":3,"stat.mineBlock.mowziesmobs.painted_acacia":16,"stat.craftItem.extrautils2.compressedcobblestone":1,"stat.swimOneCm":2787201,"stat.craftItem.securitycraft.mine":36,"stat.mineBlock.minecraft.spruce_stairs":1,"stat.useItem.chisel.planks-acacia":86,"stat.useItem.minecraft.dirt":8173,"stat.mineBlock.betternether.nether_grass":9,"stat.pickup.animalium.bear_claw_paxel":1,"stat.pickup.minecraft.enchanting_table":1,"stat.pickup.securitycraft.reinforced_metals":21,"stat.mineBlock.zawa.dried_bamboo":5,"stat.useItem.minecraft.golden_pickaxe":1,"stat.mineBlock.minecraft.magma":480,"stat.mineBlock.minecraft.carpet":3,"stat.drop.minecraft.fence":1,"stat.drop.chisel.chisel_iron":10,"stat.mineBlock.chisel.limestone2":1049,"stat.useItem.minecraft.stone_shovel":151,"stat.pickup.minecraft.clay":64,"stat.pickup.minecraft.glass_bottle":20,"stat.useItem.chisel.limestone2":397,"stat.useItem.securitycraft.reinforced_planks":136,"stat.drop.minecraft.wheat_seeds":12,"stat.drop.astralsorcery.itemgrapplewand":13,"stat.drop.astralsorcery.itemconstellationpaper":1,"stat.useItem.minecraftfuture.bamboo":21,"stat.craftItem.minecraft.wooden_slab":360,"stat.pickup.astralsorcery.itemtunedrockcrystal":14,"stat.pickup.minecraft.golden_pickaxe":1,"stat.mineBlock.astralsorcery.blockaltar":3,"stat.useItem.animalium.rat_meat_cooked":3,"stat.drop.minecraft.log":9,"stat.useItem.minecraft.sign":47,"stat.pickup.treasure2.safe":7,"stat.pickup.minecraft.mutton":6,"stat.pickup.betternether.nether_brick_tile_stairs":43,"stat.pickup.zawa.sea_urchin_tropical":2,"stat.pickup.malisisdoors.verticalhatch":4,"stat.mineBlock.zawa.large_sea_urchin":5,"stat.pickup.chisel.chisel_diamond":3,"stat.pickup.minecraft.stonebrick":14,"stat.pickup.railcraft.dust":456,"stat.useItem.minecraft.acacia_stairs":11,"stat.mineBlock.extrautils2.trashcan":5,"stat.mineBlock.minecraft.nether_brick":95,"stat.pickup.minecraftfuture.bamboo":42,"stat.drop.astralsorcery.itemwand":2,"stat.mineBlock.betternether.black_bush":2,"stat.useItem.astralsorcery.blockmarble":4442,"stat.craftItem.minecraft.brick_block":5,"stat.craftItem.minecraft.stone_slab2":0,"stat.pickup.railcraft.ore_metal":266,"stat.killEntity.rat":885,"stat.pickup.malisisdoors.big_door_rusty_3x3":3,"stat.drop.minecraft.potion":1,"stat.useItem.minecraft.stone_slab":10,"stat.craftItem.minecraft.stone":1789,"stat.mineBlock.minecraft.crafting_table":43,"stat.useItem.minecraft.diamond_pickaxe":40810,"stat.mineBlock.minecraft.quartz_block":26,"stat.useItem.minecraft.carrot":159,"stat.useItem.betternether.cincinnasite_pillar":4,"stat.useItem.leatherworks.drying_rack_oak":12,"stat.pickup.betternether.cincinnasite_pot":1,"stat.mineBlock.traverse.orange_autumnal_leaves":3,"stat.pickup.minecraft.stone_button":40,"stat.pickup.minecraft.slime_ball":89,"stat.craftItem.minecraft.diamond_pickaxe":4,"stat.craftItem.securitycraft.retinal_scanner":5,"stat.pickup.leatherworks.leather_strip":4,"stat.craftItem.minecraft.clay":257,"stat.pickup.cgm.scope":1,"stat.pickup.minecraft.gravel":854,"stat.useItem.minecraft.glass_bottle":1,"stat.useItem.minecraft.diamond_axe":122,"stat.pickup.treasure2.pirate_chest":9,"stat.pickup.extrautils2.goldenlasso":2,"stat.entityKilledBy.Guardian":8,"stat.mineBlock.treasure2.wither_log":1,"stat.pickup.leatherworks.drying_rack_spruce":35,"stat.pickup.astralsorcery.itemrockcrystalsimple":89,"stat.pickup.minecraft.stone_brick_stairs":21,"stat.drop.minecraft.cooked_porkchop":7,"stat.pickup.minecraft.diamond_sword":17,"stat.pickup.minecraft.brick":20,"stat.killEntity.SkeletonHorse":1,"stat.pickup.minecraft.iron_helmet":16,"stat.pickup.minecraft.black_shulker_box":1,"stat.pickup.treasure2.compressor_chest":2,"stat.entityKilledBy.CaveSpider":24,"stat.craftItem.minecraft.bread":82,"stat.pickup.minecraft.spider_eye":170,"stat.useItem.minecraft.stone_button":1,"stat.pickup.minecraft.experience_bottle":5,"stat.pickup.minecraft.diamond_ore":12,"stat.useItem.minecraft.cooked_chicken":14,"stat.pickup.minecraft.iron_ore":2105,"stat.pickup.chisel.planks-birch":411,"stat.mineBlock.mca.rose_gold_ore":11,"stat.craftItem.extrautils2.chickenring":2,"stat.mineBlock.treasure2.skull_and_crossbones":4,"stat.mineBlock.minecraft.iron_bars":2,"stat.pickup.treasure2.iron_key":1,"stat.pickup.minecraft.leaves":5,"stat.pickup.minecraft.leather":241,"stat.drop.minecraft.iron_hoe":2,"stat.useItem.minecraft.wooden_pickaxe":138,"stat.pickup.betternether.nether_cactus":9,"stat.pickup.minecraft.reeds":729,"stat.pickup.minecraft.prismarine_crystals":385,"stat.pickup.railcraft.tool_crowbar_seasons":1,"stat.pickup.animalium.bear_meat_cooked":11,"stat.useItem.minecraft.magma":78,"stat.craftItem.securitycraft.universal_block_modifier":1,"stat.craftItem.minecraft.glass":4499,"stat.sleepInBed":330,"stat.craftItem.minecraft.baked_potato":26,"stat.killEntity.Cow":147,"stat.pickup.minecraft.minecart":1,"stat.killEntity.Pig":50,"stat.craftItem.securitycraft.bouncing_betty":1,"stat.craftItem.minecraft.iron_sword":10,"stat.pickup.leatherworks.pack_blue":1,"stat.walkOneCm":50407433,"stat.useItem.leatherworks.drying_rack_spruce":38,"stat.playerKills":11,"stat.pickup.minecraft.clay_ball":2304,"stat.mineBlock.minecraft.trapped_chest":22,"stat.killEntity.piranha":315,"stat.craftItem.elevatorid.elevator_white":2,"stat.pickup.treasure2.spider_lock":11,"stat.useItem.minecraft.spruce_boat":10,"stat.pickup.cgm.rifle":1,"stat.pickup.extrautils2.minichest":1,"stat.mineBlock.chisel.basalt2":344,"stat.craftItem.securitycraft.codebreaker":2,"stat.pickup.minecraft.tnt":8,"stat.pickup.betternether.cincinnasite_stairs":18,"stat.drop.chisel.marble2":6,"stat.drop.chisel.marble1":1,"stat.pickup.minecraft.stone":8015,"stat.craftItem.securitycraft.cobblestone_mine":6,"stat.pickup.minecraft.silver_glazed_terracotta":64,"stat.craftItem.minecraft.hay_block":6,"stat.useItem.minecraft.leaves":4,"stat.pickup.treasure2.stone_lock":3,"stat.pickup.minecraft.gold_ingot":73,"stat.useItem.minecraft.prismarine":33,"stat.mineBlock.betternether.netherrack_moss":7,"stat.killEntity.Skeleton":416,"stat.killEntity.wild_dog":336,"stat.mineBlock.minecraft.cactus":118,"stat.mineBlock.zawa.small_sea_urchin":3,"stat.mineBlock.minecraft.redstone_torch":1,"stat.killEntity.Spider":304,"stat.pickup.minecraft.bread":17,"stat.pickup.astralsorcery.itemcraftingcomponent":159,"stat.craftItem.minecraft.spruce_fence":177,"stat.pickup.minecraft.quartz":187,"stat.craftItem.extrautils2.trashcan":3,"stat.mineBlock.extrautils2.ironwood_sapling":1,"stat.pickup.minecraft.water_bucket":10,"stat.useItem.chisel.cobblestone1":3,"stat.pickup.minecraft.spruce_stairs":2,"stat.mineBlock.betternether.egg_plant":2,"stat.mineBlock.minecraft.redstone_ore":797,"stat.useItem.chisel.cobblestone2":1029,"stat.craftItem.minecraft.coal_block":320,"stat.mineBlock.chisel.planks-oak":82,"stat.craftItem.minecraft.brick":34,"stat.mineBlock.minecraft.stone":29753,"stat.useItem.minecraft.sandstone":18}