{"stat.chestOpened":18,"stat.walkOneCm":797365,"stat.mineBlock.astralsorcery.blockmarblestairs":6,"stat.mineBlock.traverse.red_autumnal_leaves":57,"stat.useItem.minecraft.potato":22,"stat.pickup.traverse.orange_autumnal_sapling":6,"stat.leaveGame":2,"stat.mineBlock.chisel.marble2":67,"stat.useItem.minecraft.log":108,"stat.pickup.minecraft.crafting_table":3,"stat.useItem.minecraft.cobblestone":2,"stat.craftItem.minecraft.crafting_table":3,"stat.pickup.traverse.yellow_autumnal_sapling":13,"stat.useItem.minecraft.apple":9,"stat.mineBlock.traverse.yellow_autumnal_leaves":25,"stat.pickup.minecraft.string":1,"stat.pickup.minecraft.log":534,"stat.pickup.leatherworks.bark_oak":1,"stat.pickup.comforts.sleeping_bag":6,"stat.jump":2586,"stat.swimOneCm":9220,"stat.pickup.traverse.brown_autumnal_sapling":16,"stat.fallOneCm":56381,"stat.useItem.minecraft.planks":487,"stat.useItem.astralsorcery.blockmarble":79,"stat.pickup.tombstone.crafting_ingredient":1,"stat.entityKilledBy.Skeleton":1,"stat.useItem.minecraft.stone_axe":207,"stat.pickup.minecraft.stone":34,"stat.crouchOneCm":15108,"stat.pickup.minecraft.baked_potato":8,"stat.pickup.minecraft.spider_eye":1,"stat.craftItem.minecraft.chest":1,"stat.pickup.minecraft.sapling":20,"stat.pickup.minecraft.dirt":309,"stat.useItem.minecraft.dirt":184,"stat.sprintOneCm":413207,"stat.useItem.minecraft.stone_slab2":64,"stat.mineBlock.leatherworks.debarked_log_oak":1,"stat.pickup.minecraft.apple":7,"stat.craftItem.minecraft.stick":32,"stat.craftItem.minecraft.wooden_axe":1,"stat.craftingTableInteraction":23,"stat.pickup.minecraft.iron_ore":1,"stat.pickup.traverse.red_autumnal_sapling":7,"stat.pickup.minecraft.rotten_flesh":5,"stat.craftItem.minecraft.planks":914,"stat.craftItem.minecraft.stone_axe":5,"stat.useItem.chisel.marble2":65,"stat.damageTaken":4256,"stat.mineBlock.minecraft.crafting_table":2,"stat.mineBlock.astralsorcery.blockmarble":88,"stat.craftItem.minecraft.stone_pickaxe":5,"stat.mineBlock.minecraft.torch":11,"stat.useItem.minecraft.wooden_pickaxe":93,"stat.pickup.astralsorcery.itemcraftingcomponent":3,"stat.pickup.minecraft.cobblestone":176,"stat.mobKills":2,"stat.mineBlock.minecraft.log":54,"stat.pickup.minecraft.planks":224,"stat.mineBlock.chisel.limestone2":28,"stat.pickup.chisel.limestone2":28,"stat.flyOneCm":203225,"stat.mineBlock.traverse.orange_autumnal_leaves":6,"stat.mineBlock.minecraft.planks":53,"stat.deaths":14,"stat.useItem.tombstone.grave_key":22,"stat.entityKilledBy.wild_dog":1,"stat.pickup.minecraft.wheat_seeds":12,"stat.mineBlock.minecraft.leaves":6,"stat.pickup.minecraft.potato":22,"stat.playOneMinute":248670,"stat.entityKilledBy.Zombie":4,"stat.pickup.minecraft.torch":13,"stat.useItem.minecraft.stone_pickaxe":479,"stat.sneakTime":4971,"stat.damageDealt":1352,"stat.mineBlock.astralsorcery.blockcustomsandore":2,"stat.pickup.astralsorcery.blockmarble":91,"stat.mineBlock.traverse.brown_autumnal_leaves":9,"stat.pickup.astralsorcery.blockmarblestairs":6,"stat.mineBlock.minecraft.iron_ore":1,"stat.sleepInBed":19,"stat.killEntity.Zombie":2,"stat.useItem.minecraft.baked_potato":8,"stat.timeSinceDeath":5610,"stat.useItem.minecraft.wooden_axe":21,"stat.entityKilledBy.rat":1,"stat.mineBlock.minecraft.dirt":244,"stat.craftItem.minecraft.wooden_pickaxe":2,"stat.mineBlock.minecraft.stone":148,"stat.pickup.chisel.marble2":66,"stat.mineBlock.minecraft.tallgrass":39,"stat.diveOneCm":6987,"stat.pickup.minecraft.wheat":4}